pipyt/__init__.py
pipyt/__main__.py
pipyt-0.1.1.dist-info/METADATA
pipyt-0.1.1.dist-info/WHEEL
pipyt-0.1.1.dist-info/entry_points.txt
pipyt-0.1.1.dist-info/top_level.txt
pipyt-0.1.1.dist-info/RECORD
