Metadata-Version: 2.1
Name: pipyt
Version: 0.1.1
Summary: A basic CLI application that searches and downloads YT Music songs
Project-URL: Source, https://github.com/r1klz/pipyt
Project-URL: Issues, https://github.com/r1klz/pipyt/issues
Requires-Dist: click
Requires-Dist: requests
Requires-Dist: yt-dlp
Requires-Dist: columnar
